pgtools/__init__.py
pgtools/genomewrappers.py
pgtools/genomicwrappers.py
pgtools/genomicwrappers_old.py
pgtools/getsizeof.py
pgtools/gotools.py
pgtools/intervaldict.py
pgtools/intervaloverlaps.py
pgtools/motiftools.py
pgtools/myplots.py
pgtools/name_translation.py
pgtools/peaktools.py
pgtools/rnatools.py
pgtools/romannumerals.py
pgtools/tableindex.py
pgtools/toolbox.py
pgtools-0.5.0.dist-info/DESCRIPTION.rst
pgtools-0.5.0.dist-info/METADATA
pgtools-0.5.0.dist-info/RECORD
pgtools-0.5.0.dist-info/WHEEL
pgtools-0.5.0.dist-info/metadata.json
pgtools-0.5.0.dist-info/top_level.txt
