Metadata-Version: 2.0
Name: pgtools
Version: 0.5.0
Summary: A collection of useful Python code, primarily focused on bioinformatics, with particular attention to working with HOMER
Home-page: http://github.com/phageghost/pg_tools
Author: phageghost
Author-email: pgtools@phageghost.net
License: MIT
Platform: UNKNOWN
Requires-Dist: intervaltree
Requires-Dist: matplotlib
Requires-Dist: numpy
Requires-Dist: pandas
Requires-Dist: scipy
Requires-Dist: seaborn
Requires-Dist: weblogo
